src/code_splitter.py
src/command.py
src/main.py
src/utils.py
src/entities/__init__.py
src/entities/block.py
src/entities/file.py
src/services/__init__.py
src/services/attach_import_statements_service.py
src/services/generate_import_statement_service.py
src/services/load_file_service.py
src/services/move_blocks_to_new_files_service.py
src/services/update_init_file_service.py
src/types/block_type.py
src/types/lines.py
python_code_splitter-0.2.2.dist-info/METADATA
python_code_splitter-0.2.2.dist-info/WHEEL
python_code_splitter-0.2.2.dist-info/entry_points.txt
python_code_splitter-0.2.2.dist-info/licenses/LICENSE
python_code_splitter-0.2.2.dist-info/RECORD
