Metadata-Version: 2.4
Name: python-code-splitter
Version: 0.2.2
Summary: split Python code by classes and functions
Project-URL: GitHub, https://github.com/routerman/python-code-splitter
Author: routerman
License: MIT License
License-File: LICENSE
Requires-Python: >=3.9
